eniat/entry.py
eniat/config/default.yaml
eniat/core/__init__.py
eniat/core/base.py
eniat/core/course.py
eniat/scikit/__init__.py
eniat/scikit/grader.py
eniat/scikit/learner.py
eniat/torch/__init__.py
eniat/torch/grader.py
eniat/torch/learner.py
eniat/torch/predictor.py
eniat/torch/scheduler.py
eniat/torch/trainer.py
eniat/utils/__init__.py
eniat/utils/cli.py
eniat/utils/conf.py
eniat/utils/manager.py
eniat/utils/statelogger.py
eniat/utils/style.py
eniat-0.0.3.dist-info/LICENSE
eniat-0.0.3.dist-info/METADATA
eniat-0.0.3.dist-info/WHEEL
eniat-0.0.3.dist-info/entry_points.txt
eniat-0.0.3.dist-info/top_level.txt
eniat-0.0.3.dist-info/RECORD
