Metadata-Version: 2.1
Name: eniat
Version: 0.0.3
Summary: ENIAT supports and boosts your machine learning experiments!
Author-email: Cheol Woong Na <skcjfdnd1996@gmail.com>
License: MIT License
Project-URL: Homepage, https://github.com/GimmeSpoon/ENIAT
Project-URL: Bug Tracker, https://github.com/GimmeSpoon/ENIAT/issues
Project-URL: Repository, https://github.com/GimmeSpoon/ENIAT
Classifier: Development Status :: 2 - Pre-Alpha
Classifier: Programming Language :: Python :: 3
Classifier: Programming Language :: Python :: 3.8
Classifier: Programming Language :: Python :: 3.9
Classifier: Programming Language :: Python :: 3.10
Classifier: Programming Language :: Python :: 3.11
Classifier: Programming Language :: Python :: 3.12
Classifier: Programming Language :: Python :: 3.13
Classifier: License :: OSI Approved :: MIT License
Classifier: Operating System :: OS Independent
Classifier: Intended Audience :: Science/Research
Classifier: Topic :: Scientific/Engineering
Classifier: Topic :: Scientific/Engineering :: Artificial Intelligence
Classifier: Topic :: Software Development
Classifier: Topic :: Software Development :: Libraries
Classifier: Topic :: Software Development :: Libraries :: Python Modules
Requires-Python: >=3.8
License-File: LICENSE
Requires-Dist: omegaconf
Requires-Dist: openpyxl
Requires-Dist: numpy
Requires-Dist: rich[jupyter]
Requires-Dist: importlib-resources
